melar/__init__.py
melar/cfuncs.py
melar/main.py
mlr_gd-0.2.1.dist-info/LICENSE
mlr_gd-0.2.1.dist-info/METADATA
mlr_gd-0.2.1.dist-info/WHEEL
mlr_gd-0.2.1.dist-info/top_level.txt
mlr_gd-0.2.1.dist-info/RECORD
