Metadata-Version: 2.2
Name: mlr-gd
Version: 0.2.1
Summary: A package for multiple linear regression by gradient descent.
Home-page: https://github.com/DrSolidDevil/mlr-gd/
Author: DrSolidDevil
License: BSD 3-Clause
Keywords: linear regression,linear,regression,gradient descent,machine learning,artificial intelligence
Classifier: License :: OSI Approved :: BSD License
Classifier: Programming Language :: Python :: 3.11
Classifier: Operating System :: OS Independent
Classifier: Intended Audience :: Developers
Classifier: Intended Audience :: Science/Research
Classifier: Topic :: Scientific/Engineering :: Artificial Intelligence
Requires-Python: >=3.11
License-File: LICENSE
Requires-Dist: numpy>=2.2.1
Provides-Extra: dev
Requires-Dist: twine>=6.0.1; extra == "dev"
Requires-Dist: pandas>=2.2.3; extra == "dev"
Requires-Dist: pytest>=8.3.4; extra == "dev"
Requires-Dist: setuptools>=75.8.0; extra == "dev"
Dynamic: author
Dynamic: classifier
Dynamic: description
Dynamic: description-content-type
Dynamic: home-page
Dynamic: keywords
Dynamic: license
Dynamic: provides-extra
Dynamic: requires-dist
Dynamic: requires-python
Dynamic: summary
